main.py
modmon-0.0.0a7.dist-info/METADATA
modmon-0.0.0a7.dist-info/WHEEL
modmon-0.0.0a7.dist-info/top_level.txt
modmon-0.0.0a7.dist-info/RECORD
