Metadata-Version: 2.1
Name: modmon
Version: 0.0.0a7
Summary: A self-host first performant ml-ops platform
Author-email: Karam Ravindra <contact@karanravindra.me>
